radicale_bsdauth/__init__.py
radicale_bsdauth-1.0.1.dist-info/METADATA
radicale_bsdauth-1.0.1.dist-info/WHEEL
radicale_bsdauth-1.0.1.dist-info/top_level.txt
radicale_bsdauth-1.0.1.dist-info/RECORD
