Metadata-Version: 2.1
Name: radicale-bsdauth
Version: 1.0.1
Summary: Login to Radicale with your native OpenBSD accounts.
Home-page: https://github.com/kousu/radicale-bsdauth
Author-email: kousu <kousu@kousu.ca>
License: GPL version 3
Project-URL: Homepage, https://github.com/kousu/radicale-bsdauth
Project-URL: Repository, https://github.com/kousu/radicale-bsdauth
Project-URL: Documentation, https://github.com/kousu/radicale-bsdauth/blob/trunk/README.md
Keywords: authentication,radicale,caldav,carddav,PIM,plugin
Platform: UNKNOWN
Requires-Python: >=3.8
Requires-Dist: radicale (~=3.0)
